<?xml version="1.0" encoding="UTF-8"?>
<!DOCTYPE mapper PUBLIC "-//mybatis.org//DTD Mapper 3.0//EN" 
	"http://mybatis.org/dtd/mybatis-3-mapper.dtd">

<mapper namespace="com.ssafy.enjoytrip.attraction.mapper.AttractionMapper">

	<resultMap type="attractionDto" id="attraction">
		<result column="content_no" property="contentNo" />
		<result column="content_type_id" property="contentTypeId" />
		<result column="title" property="title" />
		<result column="addr1" property="addr1" />
		<result column="addr2" property="addr2" />
		<result column="zipcode" property="zipcode" />
		<result column="first_image" property="firstImage" />
		<result column="loc_no" property="locNo" />
	</resultMap>
	
	<resultMap type="attractionLikeDto" id="attractionLike">
		<result column="favorite_no" property="favoriteNo" />
		<result column="content_no" property="contentNo" />
		<result column="user_no" property="userNo" />
		<result column="registration_date" property="registDate" />
	</resultMap>
	
	<select id="listAttr" resultMap="attraction">
		select *
		from attraction_info 
		where loc_no = #{locNo}
	</select>
	
	<select id="listAttrAll" resultMap="attraction">
		select *
		from attraction_info 
		where loc_no = #{locNo} and content_type_id=#{contentTypeId}
	</select>
	
    <select id="getAttraction" resultMap="attraction">
       select *
       from attraction_info
       where content_no = #{contentNo}
    </select>

	<select id="getLikeCount" parameterType="int" resultType="int">
		select count(favorite_no)
		from favorite_place
		where content_no = #{contentNo}
	</select>
	
	<select id="getLikeList" parameterType="int" resultMap = "attractionLike">
		select *
		from favorite_place
		where content_no = #{contentNo}
	</select>
	
	<insert id="likeAttraction" parameterType="attractionLikeDto">
		insert into favorite_place (content_no, user_no, registration_date)
		values (#{contentNo}, #{userNo}, now())
	</insert>
    
    <select id="getLikeAttrList" parameterType="int" resultMap="attraction">
		select a.content_no, a.content_type_id, a.title, a.addr1, a.addr2, a.zipcode, a.first_image, a.loc_no
		from favorite_place f join attraction_info a
		using (content_no)
		where f.user_no = #{userNo}
		order by f.favorite_no
	</select>

	<select id="getLikeCountBySido" resultType="map">
		select s.sido_name 'name', count(f.favorite_no) 'likeCnt' from
		favorite_place f, attraction_info attr, sido s
		where f.content_no = attr.content_no
		and floor(attr.loc_no/1000) = s.sido_no
		group by s.sido_name
		order by count(f.favorite_no) desc
	</select>
</mapper>